atscale/.DS_Store
atscale/__init__.py
atscale/base/__init__.py
atscale/base/config.py
atscale/base/endpoints.py
atscale/base/enums.py
atscale/base/parent_enums.py
atscale/base/private_enums.py
atscale/base/templates.py
atscale/catalog/__init__.py
atscale/catalog/catalog.py
atscale/client/__init__.py
atscale/client/client.py
atscale/connection/__init__.py
atscale/connection/connection.py
atscale/data_model/__init__.py
atscale/data_model/data_model.py
atscale/data_model/dm_helpers/__init__.py
atscale/data_model/dm_helpers/dmv_helpers.py
atscale/data_model/dm_helpers/metadata_helpers.py
atscale/data_model/dm_helpers/model_validation_helpers.py
atscale/data_model/dm_helpers/query_gen_helpers.py
atscale/db/__init__.py
atscale/db/connections/__init__.py
atscale/db/connections/bigquery.py
atscale/db/connections/databricks.py
atscale/db/connections/iris.py
atscale/db/connections/postgres.py
atscale/db/connections/snowflake.py
atscale/db/sql_connection.py
atscale/db/sqlalchemy_connection.py
atscale/errors/__init__.py
atscale/errors/atscale_errors.py
atscale/parsers/__init__.py
atscale/parsers/dictionary_parser.py
atscale/repo/__init__.py
atscale/repo/repo.py
atscale/sml_objects/__init__.py
atscale/sml_objects/object_classes/__init__.py
atscale/sml_objects/object_classes/aggregate_object.py
atscale/sml_objects/object_classes/alias_object.py
atscale/sml_objects/object_classes/alternate_object.py
atscale/sml_objects/object_classes/attribute_reference_object.py
atscale/sml_objects/object_classes/calculated_member_object.py
atscale/sml_objects/object_classes/calculation_group_object.py
atscale/sml_objects/object_classes/calculation_object.py
atscale/sml_objects/object_classes/catalog_object.py
atscale/sml_objects/object_classes/column_object.py
atscale/sml_objects/object_classes/connection_object.py
atscale/sml_objects/object_classes/dataset_object.py
atscale/sml_objects/object_classes/dataset_properties_object.py
atscale/sml_objects/object_classes/dialect_object.py
atscale-3.1.0.dist-info/LICENSE.md
atscale-3.1.0.dist-info/METADATA
atscale-3.1.0.dist-info/WHEEL
atscale-3.1.0.dist-info/RECORD
